README.md
fp_functions.py
setup.py
fp_functions.egg-info/PKG-INFO
fp_functions.egg-info/SOURCES.txt
fp_functions.egg-info/dependency_links.txt
fp_functions.egg-info/top_level.txt