Metadata-Version: 2.1
Name: fp-functions
Version: 0.1.1
Summary: A small Python library that adds some functional programming features
Home-page: UNKNOWN
Author: Thomas Gregory
License: Apache License, Version 2.0
Platform: UNKNOWN
Requires: more_itertools
